setup.py
upsearch/__init__.py
upsearch/main.py
upsearch.egg-info/PKG-INFO
upsearch.egg-info/SOURCES.txt
upsearch.egg-info/dependency_links.txt
upsearch.egg-info/entry_points.txt
upsearch.egg-info/not-zip-safe
upsearch.egg-info/pbr.json
upsearch.egg-info/requires.txt
upsearch.egg-info/top_level.txt