Metadata-Version: 1.0
Name: upsearch
Version: 0.2
Summary: App for finding file in nearest parent folder
Home-page: https://github.com/nvbn/upsearch
Author: Vladimir Iakovlev
Author-email: nvbn.rm@gmail.com
License: MIT
Platform: UNKNOWN
